pytandem/__init__.py
pytandem/pytandem.py
pytandem-1.0.1.dist-info/LICENSE
pytandem-1.0.1.dist-info/METADATA
pytandem-1.0.1.dist-info/WHEEL
pytandem-1.0.1.dist-info/top_level.txt
pytandem-1.0.1.dist-info/RECORD
