Metadata-Version: 2.1
Name: pytandem
Version: 1.0.1
Summary: A multi-threaded event manager package for triggering methods in tandem groups
Home-page: https://github.com/rexeron/pytandem
Author: Kieren Coetzee
Author-email: kieren.c.coetzee@gmail.com
License: UNKNOWN
Project-URL: Bug Tracker, https://github.com/rexeron/pytandem/issues
Platform: UNKNOWN
Classifier: Programming Language :: Python :: 3
Classifier: License :: OSI Approved :: MIT License
Classifier: Operating System :: OS Independent
Requires-Python: >=3.6
License-File: LICENSE
